MANIFEST.in
README.txt
setup.py
zope2.zodbbrowser-configure.zcml
docs/HISTORY.txt
zope2/__init__.py
zope2.zodbbrowser.egg-info/PKG-INFO
zope2.zodbbrowser.egg-info/SOURCES.txt
zope2.zodbbrowser.egg-info/dependency_links.txt
zope2.zodbbrowser.egg-info/entry_points.txt
zope2.zodbbrowser.egg-info/namespace_packages.txt
zope2.zodbbrowser.egg-info/not-zip-safe
zope2.zodbbrowser.egg-info/requires.txt
zope2.zodbbrowser.egg-info/top_level.txt
zope2/zodbbrowser/README.txt
zope2/zodbbrowser/__init__.py
zope2/zodbbrowser/bottom.py
zope2/zodbbrowser/configure.zcml
zope2/zodbbrowser/interfaces.py
zope2/zodbbrowser/left.py
zope2/zodbbrowser/right.py
zope2/zodbbrowser/tests.py
zope2/zodbbrowser/version.txt
zope2/zodbbrowser/zodbbrowser.py
zope2/zodbbrowser/zope2.py
zope2/zodbbrowser/resources/icons.gif
zope2/zodbbrowser/resources/jquery.dynatree.js
zope2/zodbbrowser/resources/jquery.js
zope2/zodbbrowser/resources/jquery.layout.js
zope2/zodbbrowser/resources/jquery.ui.js
zope2/zodbbrowser/resources/loading.gif
zope2/zodbbrowser/resources/sourcecode.css
zope2/zodbbrowser/resources/ui.dynatree.css
zope2/zodbbrowser/resources/vline.gif
zope2/zodbbrowser/resources/zodbbrowser.css
zope2/zodbbrowser/resources/zodbbrowser.js
zope2/zodbbrowser/resources/zodblogo.png
zope2/zodbbrowser/templates/zodbbrowser.zpt