Metadata-Version: 1.0
Name: zope2.zodbbrowser
Version: 0.2
Summary: A zodb browser for Zope2
Home-page: http://code.google.com/p/zodbbrowser
Author: Roberto Allende - Menttes SRL
Author-email: rover@menttes.com
License: GPL
Keywords: zope2 zope zodb python
Platform: UNKNOWN
Classifier: Programming Language :: Python
